debuggy/__init__.py
debuggy/core.py
stalkoverflow/__init__.py
stalkoverflow/__main__.py
stalkoverflow/animation.py
stalkoverflow/color.py
stalkoverflow/editor_tui.py
stalkoverflow/handler.py
stalkoverflow/parsers.py
stalkoverflow/ui.py
debuggy-3.0.1.dist-info/LICENSE
debuggy-3.0.1.dist-info/METADATA
debuggy-3.0.1.dist-info/WHEEL
debuggy-3.0.1.dist-info/entry_points.txt
debuggy-3.0.1.dist-info/top_level.txt
debuggy-3.0.1.dist-info/RECORD
