Metadata-Version: 2.1
Name: debuggy
Version: 3.0.1
Summary: Stalk StackOverflow.
Home-page: https://github.com/derhnyel/deBuggy
Author: Eje Daniel
Author-email: ejedenials@gmail.com
License: MIT License        
Keywords: debuggy python package stalkoverflow
Platform: UNKNOWN
Classifier: Programming Language :: Python :: 3
Classifier: License :: OSI Approved :: MIT License
Classifier: Operating System :: OS Independent
Requires-Python: >=3
License-File: LICENSE
Requires-Dist: bs4 (==0.0.1)
Requires-Dist: argparse (==1.4.0)
Requires-Dist: pyfiglet (==0.8.post1)
Requires-Dist: psutil (==5.8.0)
Requires-Dist: pyperclip (==1.7.0)
Requires-Dist: colorama (==0.4.4)
Requires-Dist: requests (==2.27.1)
Requires-Dist: distro (==1.6.0)
Requires-Dist: fake-useragent (==0.1.11)
Provides-Extra: win
Requires-Dist: windows-curses ; extra == 'win'
